[{"Name":"cameraport","Value":"2","Values":["0: None","1: Port →","2: Port ↑"]},{"Name":"scaleexposuretimetobinning","Value":"True"},{"Name":"syncexposuretime","Value":"True"},{"Name":"aoiwidth","Value":"1024","Min":"1","Max":"1024"},{"Name":"aoiheight","Value":"1024","Min":"1","Max":"1024"},{"Name":"aoileft","Value":"1","Min":"1","Max":"1024"},{"Name":"aoibottom","Value":"1","Min":"1","Max":"1024"},{"Name":"frameaveraging","Value":"0","Values":["0: 1","1: 2","2: 4","3: 8","4: 16"]},{"Name":"hfboostenabled","Value":"False"},{"Name":"hfboostfilterwidth","Value":"1,0","Min":"0,2","Max":"10"},{"Name":"hfboostweighting","Value":"0,6","Min":"0,1","Max":"0,9"},{"Name":"overlap","Value":"False"},{"Name":"temperaturesetpoint","Value":"-50","Min":"-120","Max":"20"},{"Name":"horizontalshiftspeed","Value":"0","Values":["0: 30 MHz - 16 bit","1: 10 MHz - 16 bit"]},{"Name":"outputamplifier","Value":"0","Values":["0: Electron Multiplying"]},{"Name":"preampgain","Value":"1","Values":["0: 1x","1: 2x"]},{"Name":"emadvanced","Value":"False"},{"Name":"emgain","Value":"101","Min":"0","Max":"300"},{"Name":"verticalshiftspeed","Value":"1","Values":["0: 4,33 µs","1: [2,2 µs]","2: [1,13 µs]","3: [0,6 µs]"]},{"Name":"emissionshutteropen","Value":"True"},{"Name":"verticalclockvoltage","Value":"0","Values":["0: Normal","1: +1","2: +2","3: +3","4: +4"]},{"Name":"fanmode","Value":"0","Values":["0: On (Full)","1: On (Low)","2: Off"]},{"Name":"triggermode","Value":"0","Values":["0: Normal","1: External"]},{"Name":"externaltriggertimeout","Value":"10 s","Min":"1 s","Max":"365 d"},null,{"Name":"fullsensoraoi","Value":"True"},{"Name":"pre-definedaoi","Value":"0","Values":["0: 1024 x 1024","1: 512 x 512","2: 256 x 256","3: 128 x 128","4: Custom"]},{"Name":"cameramappingminfeature","Value":"480","Min":"0","Max":"65535"},{"Name":"cameramappingminrangefeature","Value":"200","Min":"10","Max":"65535"}]